gemf/__init__.py
gemf/dump.py
gemf/gemf.py
gemf/gemf_dump.py
gemf/plot.py
gemf/tiles.py
gemf/utils.py
gemf_map-0.4.0.dist-info/licenses/LICENSE
gemf_map-0.4.0.dist-info/METADATA
gemf_map-0.4.0.dist-info/WHEEL
gemf_map-0.4.0.dist-info/top_level.txt
gemf_map-0.4.0.dist-info/RECORD
