Metadata-Version: 2.4
Name: gemf_map
Version: 0.4.0
Summary: GEMF, an efficient tile-based map format.
Author-email: Colin Moldenhauer <colin.moldenhauer@tum.de>
Project-URL: Homepage, https://github.com/ColinMoldenhauer/GEMF
Project-URL: Issues, https://github.com/ColinMoldenhauer/GEMF/issues
Keywords: gemf,tiles,map,mobile map,locus
Classifier: Programming Language :: Python :: 3
Classifier: License :: OSI Approved :: GNU General Public License v3 (GPLv3)
Classifier: Operating System :: OS Independent
Requires-Python: >=3.8
License-File: LICENSE
Provides-Extra: test
Requires-Dist: pytest>=4.6; extra == "test"
Requires-Dist: pytest-cov; extra == "test"
Requires-Dist: mercantile; extra == "test"
Provides-Extra: plot
Requires-Dist: matplotlib; extra == "plot"
Requires-Dist: folium; extra == "plot"
Dynamic: license-file
